[
  {
    "id": 1,
    "name": "Michael",
    "image": "https://upload.wikimedia.org/wikipedia/en/thumb/7/77/Michael_Weston.jpg/220px-Michael_Weston.jpg"
  },
  {
    "id": 2,
    "name": "Fiona",
    "image": "https://upload.wikimedia.org/wikipedia/en/thumb/7/70/Fiona_Glenanne.jpg/220px-Fiona_Glenanne.jpg"
  },
  {
    "id": 3,
    "name": "Sam",
    "image": "https://upload.wikimedia.org/wikipedia/en/thumb/c/c0/Sam_Axe-Burn_Notice.jpg/220px-Sam_Axe-Burn_Notice.jpg"
  },
  {
    "id": 4,
    "name": "Jesse",
    "image": "http://tvdramawatch.com/wp-content/uploads/2010/12/CobyBell.jpg"
  },
  {
    "id": 5,
    "name": "Mom",
    "image": "https://upload.wikimedia.org/wikipedia/en/thumb/1/12/Madeline_Westen.jpg/220px-Madeline_Westen.jpg"
  },
  {
    "id": 6,
    "name": "Pearce",
    "image": "http://vignette3.wikia.nocookie.net/burnnotice/images/3/3f/506galat115305PIERCE.png/revision/latest?cb=20120927232104"
  },
  {
    "id": 7,
    "name": "Strong",
    "image": "https://vignette.wikia.nocookie.net/criminalminds/images/a/a6/Jack_Coleman.jpg/revision/latest?cb=20171212043102"
  },
  {
    "id": 8,
    "name": "Larry",
    "image": "http://images.buddytv.com/btv_2_505532356_0_350_10000_-1_/burn-notice-dead-lar.jpg"
  },
  {
    "id": 9,
    "name": "James",
    "image": "https://i.pinimg.com/474x/89/f5/51/89f55119f4b3603fd76b8e833d154793.jpg"
  },
  {
    "id": 10,
    "name": "Anson",
    "image": "https://vignette.wikia.nocookie.net/burnnotice/images/2/2a/Anson.jpg/revision/latest?cb=20111112235027"
  },
  {
    "id": 11,
    "name": "Chris",
    "image": "https://vignette.wikia.nocookie.net/burnnotice/images/a/a1/Mason-gilroy.jpg/revision/latest?cb=20121228232947"
  },
  {
    "id": 12,
    "name": "Marc",
    "image": "https://images-na.ssl-images-amazon.com/images/M/MV5BMjA2ODQwMjIzOF5BMl5BanBnXkFtZTcwNzg1ODk0Mw@@._V1_UY317_CR6,0,214,317_AL_.jpg"
  }
]
